diffjpeg_jax/__init__.py
diffjpeg_jax/diffjpeg.py
diffjpeg_jax-1.0.0.dist-info/LICENSE
diffjpeg_jax-1.0.0.dist-info/METADATA
diffjpeg_jax-1.0.0.dist-info/WHEEL
diffjpeg_jax-1.0.0.dist-info/RECORD
