Metadata-Version: 2.1
Name: diffjpeg_jax
Version: 1.0.0
Summary: DiffJPEG implemented in JAX
Author: Haydn Jones
Author-email: haydnjonest@gmail.com
Requires-Python: >=3.7,<4.0
Classifier: Programming Language :: Python :: 3
Classifier: Programming Language :: Python :: 3.7
Classifier: Programming Language :: Python :: 3.8
Classifier: Programming Language :: Python :: 3.9
Classifier: Programming Language :: Python :: 3.10
Classifier: Programming Language :: Python :: 3.11
Classifier: Programming Language :: Python :: 3.12
Requires-Dist: jaxtyping (>=0.2,<0.3)
